kahi_impactu_post_cites_count/Kahi_impactu_post_cites_count.py
kahi_impactu_post_cites_count/__init__.py
kahi_impactu_post_cites_count/_version.py
Kahi_impactu_post_cites_count-0.0.4a0.dist-info/LICENSE
Kahi_impactu_post_cites_count-0.0.4a0.dist-info/METADATA
Kahi_impactu_post_cites_count-0.0.4a0.dist-info/WHEEL
Kahi_impactu_post_cites_count-0.0.4a0.dist-info/top_level.txt
Kahi_impactu_post_cites_count-0.0.4a0.dist-info/RECORD
