Metadata-Version: 2.2
Name: Kahi_impactu_post_cites_count
Version: 0.0.4a0
Summary: Kahi plugin post calculation of cites count for impactu
Home-page: https://github.com/colav/Kahi_plugins
Author: Colav
Author-email: colav@udea.edu.co
License: BSD
License-File: LICENSE
Requires-Dist: kahi
Dynamic: author
Dynamic: author-email
Dynamic: description
Dynamic: description-content-type
Dynamic: home-page
Dynamic: license
Dynamic: requires-dist
Dynamic: summary
